.hgignore
CHANGES.txt
LICENSE.txt
README.txt
bootstrap.py
buildout.cfg
setup.py
js/__init__.py
js.socialshareprivacy.egg-info/PKG-INFO
js.socialshareprivacy.egg-info/SOURCES.txt
js.socialshareprivacy.egg-info/dependency_links.txt
js.socialshareprivacy.egg-info/entry_points.txt
js.socialshareprivacy.egg-info/namespace_packages.txt
js.socialshareprivacy.egg-info/not-zip-safe
js.socialshareprivacy.egg-info/requires.txt
js.socialshareprivacy.egg-info/top_level.txt
js/socialshareprivacy/__init__.py
js/socialshareprivacy/test_jquery.socialshareprivacy.txt
js/socialshareprivacy/resources/2-klick-logo_min.jpg
js/socialshareprivacy/resources/Makefile
js/socialshareprivacy/resources/README.txt
js/socialshareprivacy/resources/dimensions.gif
js/socialshareprivacy/resources/index.html
js/socialshareprivacy/resources/jquery.socialshareprivacy.js
js/socialshareprivacy/resources/jquery.socialshareprivacy.min.js
js/socialshareprivacy/resources/socialshareprivacy/socialshareprivacy.css
js/socialshareprivacy/resources/socialshareprivacy/images/2-klick-logo.jpg
js/socialshareprivacy/resources/socialshareprivacy/images/dummy_facebook.png
js/socialshareprivacy/resources/socialshareprivacy/images/dummy_facebook_dark.png
js/socialshareprivacy/resources/socialshareprivacy/images/dummy_facebook_en.png
js/socialshareprivacy/resources/socialshareprivacy/images/dummy_facebook_like.png
js/socialshareprivacy/resources/socialshareprivacy/images/dummy_facebook_share_de.png
js/socialshareprivacy/resources/socialshareprivacy/images/dummy_facebook_share_de_dark.png
js/socialshareprivacy/resources/socialshareprivacy/images/dummy_facebook_share_en.png
js/socialshareprivacy/resources/socialshareprivacy/images/dummy_facebook_share_en_dark.png
js/socialshareprivacy/resources/socialshareprivacy/images/dummy_gplus.png
js/socialshareprivacy/resources/socialshareprivacy/images/dummy_gplus_alt.png
js/socialshareprivacy/resources/socialshareprivacy/images/dummy_gplus_dark.png
js/socialshareprivacy/resources/socialshareprivacy/images/dummy_twitter.png
js/socialshareprivacy/resources/socialshareprivacy/images/dummy_twitter_dark.png
js/socialshareprivacy/resources/socialshareprivacy/images/facebook_share_de.png
js/socialshareprivacy/resources/socialshareprivacy/images/facebook_share_de_dark.png
js/socialshareprivacy/resources/socialshareprivacy/images/facebook_share_en.png
