Metadata-Version: 1.0
Name: js.socialshareprivacy
Version: 1.5
Summary: Fanstatic packaging of jquery.socialshareprivacy
Home-page: UNKNOWN
Author: Fanstatic Developers
Author-email: fanstatic@googlegroups.com
License: BSD
Platform: UNKNOWN
